pydaddy/__console__.py
pydaddy/__init__.py
pydaddy/analysis.py
pydaddy/characterize.py
pydaddy/daddy.py
pydaddy/fitters.py
pydaddy/metrics.py
pydaddy/preprocessing.py
pydaddy/sde.py
pydaddy/visualize.py
pydaddy/data/fish_data/ectropus.csv
pydaddy/data/model_data/scalar/pairwise.csv
pydaddy/data/model_data/scalar/ternary.csv
pydaddy/data/model_data/vector/pairwise.csv
pydaddy/data/model_data/vector/ternary.csv
pydaddy/report/report
pydaddy/tests/__init__.py
pydaddy/tests/test_simulate.py
pydaddy/tests/tests.py
pydaddy-1.0.0.data/data/requirements.txt
pydaddy-1.0.0.dist-info/LICENSE.txt
pydaddy-1.0.0.dist-info/METADATA
pydaddy-1.0.0.dist-info/WHEEL
pydaddy-1.0.0.dist-info/entry_points.txt
pydaddy-1.0.0.dist-info/top_level.txt
pydaddy-1.0.0.dist-info/RECORD
