Metadata-Version: 2.1
Name: pydaddy
Version: 1.0.0
Summary: Package to analyse stochastic time series data
Home-page: https://github.com/tee-lab/pydaddy
Author: Ashwin Karichannavar
Author-email: ashwinkk.23@gmail.com
Classifier: Development Status :: 4 - Beta
Classifier: Environment :: Console
Classifier: Intended Audience :: Science/Research
Classifier: Intended Audience :: Education
Classifier: License :: OSI Approved :: GNU General Public License v3 (GPLv3)
Classifier: Operating System :: Microsoft :: Windows :: Windows 10
Classifier: Operating System :: MacOS :: MacOS X
Classifier: Operating System :: Unix
Classifier: Programming Language :: Python :: Implementation
Classifier: Programming Language :: Python :: 3 :: Only
Classifier: Topic :: Scientific/Engineering :: Information Analysis
Classifier: Topic :: Scientific/Engineering :: Visualization
Classifier: Topic :: Scientific/Engineering :: Mathematics
Classifier: Topic :: Scientific/Engineering :: Physics
Classifier: Topic :: Documentation :: Sphinx
License-File: LICENSE.txt
Requires-Dist: matplotlib (>=3.2)
Requires-Dist: scipy (>=1.6)
Requires-Dist: numpy (>=1.20)
Requires-Dist: seaborn (>=0.11)
Requires-Dist: tqdm (>=4.62)
Requires-Dist: plotly (>=5.5)
Requires-Dist: sdeint (>=0.2)
Requires-Dist: scikit-learn (>=0.24)
Requires-Dist: pandas (>=1.3)
Requires-Dist: notebook (>=5.3)
Requires-Dist: nbconvert (>=5.6)
Requires-Dist: setuptools (>=57.0)
